{"sculptures":[{"name":"soldier sculpture","basePrice":20,"baseWeight":10,"id":"1"},{"id":"2","name":"greek sculpture","basePrice":20,"baseWeight":20},{"id":"3","name":"cat sculpture","basePrice":30,"baseWeight":30},{"name":"test2223","basePrice":2,"baseWeight":4,"id":"ceaf6f3a-097c-43c4-9037-0e139205f3ec"},{"name":"rares-12","basePrice":3,"baseWeight":3,"id":"eff6279c-9885-4f85-abb6-1428968e8b9f"},{"name":"rares-00000","basePrice":5,"baseWeight":5,"id":"51ea8d25-9380-4d33-9007-e8aeee8388fc"},{"name":"astastastas","basePrice":5,"baseWeight":5,"id":"29660267-1370-4c6d-bae1-51945fb838ad"},{"name":"rares___test","basePrice":3,"baseWeight":7,"id":"85eca3cf-84aa-4ad7-b7d4-e56472d76e35"},{"name":"rares-s-2","basePrice":5,"baseWeight":4,"id":"2d0fbf8f-f08c-4319-b6bb-713cd8a20a5c"},{"name":"vasi","basePrice":34,"baseWeight":234,"id":"fe4cdb58-dc6b-476b-9553-2fc6521c7974"},{"name":"aaaa23","basePrice":3,"baseWeight":5,"id":"b8387d16-9b7a-42bf-8241-a359e51bae39"},{"name":"test1234566","basePrice":5,"baseWeight":5,"id":"8b371b90-e31b-4626-b89f-386db019b0ac"}],"orders":[{"id":"1","buyerName":"Rares","deliveryAddress":"bla bla bla","configuredSculptures":[{"material":"WOOD","sculpture":{"id":"1","name":"soldier sculpture","basePrice":20,"baseWeight":10}},{"material":"BRONZE","sculpture":{"id":"2","name":"greek sculpture","basePrice":20,"baseWeight":20}}]},{"id":"2","buyerName":"Rares","deliveryAddress":"bla bla bla 2","configuredSculptures":[{"material":"PLATINUM","sculpture":{"id":"3","name":"cat sculpture","basePrice":30,"baseWeight":30}}]},{"id":"aeab1192-c49a-4d3d-aa67-a37b9dad709a","buyerName":"rares b","buyerDeliveryAddress":"asdasdasdasd","configuredSculptures":[{"sculpture":{"name":"rares___test","basePrice":3,"baseWeight":7,"id":"85eca3cf-84aa-4ad7-b7d4-e56472d76e35"},"material":"BRONZE"}]},{"id":"b46d2f4b-69f0-4fcb-8a65-4ae7b0fde5ca","buyerName":"rares","buyerDeliveryAddress":"rares address","configuredSculptures":[]},{"id":"060ae9dc-50d3-423c-82cf-585fd488959d","buyerName":"dasdaeee","buyerDeliveryAddress":"dasdasdasd","configuredSculptures":[]},{"id":"8fdea290-6f65-4146-b0fb-5fdc39f04fbf","buyerName":"dasdasdasd","buyerDeliveryAddress":"sadasdasdasd","configuredSculptures":[]},{"id":"5cc57520-87cd-4eca-afa5-746c45211f75","buyerName":"dasdasd","buyerDeliveryAddress":"asdasdsad","configuredSculptures":[]},{"id":"9e7cdd19-abea-4c8a-9ec6-85a051d41f7c","buyerName":"dsadasd","buyerDeliveryAddress":"sadasd","configuredSculptures":[{"sculpture":{"id":"1","name":"soldier sculpture","basePrice":20,"baseWeight":10},"material":"WOOD"}]},{"id":"a54f5add-5130-491a-b935-b6a0c479d949","buyerName":"sadasd","buyerDeliveryAddress":"asdasd","configuredSculptures":[{"sculpture":{"name":"vasi","basePrice":34,"baseWeight":234,"id":"fe4cdb58-dc6b-476b-9553-2fc6521c7974"},"material":"BRONZE"}]}]}